growexx_multiply/__init__.py
growexx_multiply/multiplication.py
growexx_multiply-0.1.0.dist-info/METADATA
growexx_multiply-0.1.0.dist-info/WHEEL
growexx_multiply-0.1.0.dist-info/top_level.txt
growexx_multiply-0.1.0.dist-info/RECORD
